fraud_api/__init__.py
fraud_api/predictor.py
fraud_api/assets/catboost.cbm
fraud_api/assets/feature_order.json
fraud_api/assets/iso_calibrator.pkl
fraud_det-0.0.1.dist-info/licenses/LICENCE
fraud_det-0.0.1.dist-info/METADATA
fraud_det-0.0.1.dist-info/WHEEL
fraud_det-0.0.1.dist-info/top_level.txt
fraud_det-0.0.1.dist-info/RECORD
