Metadata-Version: 2.4
Name: fraud-det
Version: 0.0.1
Summary: Fraud probability prediction using CatBoost with isotonic calibration
Author: Tony
License: MIT
Classifier: Programming Language :: Python :: 3
Classifier: License :: OSI Approved :: MIT License
Classifier: Operating System :: OS Independent
Requires-Python: >=3.9
License-File: LICENCE
Requires-Dist: numpy>=1.23
Requires-Dist: pandas>=2.0
Requires-Dist: joblib>=1.2
Requires-Dist: scikit-learn>=1.3
Requires-Dist: catboost>=1.2
Dynamic: author
Dynamic: classifier
Dynamic: description
Dynamic: description-content-type
Dynamic: license
Dynamic: license-file
Dynamic: requires-dist
Dynamic: requires-python
Dynamic: summary
